EasyExcel/__init__.py
EasyExcel/converter.py
EasyExcel/test_converter.py
EasyExcel-1.1.0.dist-info/LICENSE
EasyExcel-1.1.0.dist-info/METADATA
EasyExcel-1.1.0.dist-info/WHEEL
EasyExcel-1.1.0.dist-info/top_level.txt
EasyExcel-1.1.0.dist-info/RECORD
