Metadata-Version: 2.1
Name: EasyExcel
Version: 1.1.0
Summary: A small library to interact with python and excel
Home-page: https://github.com/JoshHumpherey/EasyExcel
Author: Josh Humphrey
Author-email: jhumphrey321@gmail.com
License: UNKNOWN
Platform: UNKNOWN
Classifier: License :: OSI Approved :: MIT License
Classifier: Operating System :: OS Independent
